{"searching":"Søker...","invitationdescr":"Du har blitt invitert til følgende gruppe:","documentation":"Dokumentasjon","registernewgroup":"Opprett en ny gruppe","available":"Tilgjengelig","acceptinvite":"Aksepter invitasjonen til å bli med i gruppen","registerinfo":"Registrer og administrer dine applikasjoner og APIer.","delete1":"Er du helt sikker på at du vil slette denne gruppen?","cancel":"Avbryt","apigks":"API Gatekeepere","isexperimental":"Denne tjenesten er eksperimentell","createnewgroup":"Opprett ny gruppe","forquestions":"For spørsmål","wascreated":"Denne gruppen ble opprettet","name":"Navn","addedreject":"Avslå, og forlat gruppen","noresults":"Ingen resultater funnet","members":"Medlemmer","leave1":"Er du helt sikker på at du vil forlate gruppen?","actmakeadmin":"Sett som administrator","delete2":"Du vil ikke kunne opprette en ny gruppe igjen med samme identifikator. Data kan være assosiert med denne gruppen, og dermed bli utilgjengelig.","required":"Påkrevd","addedinfo":"En av gruppens administratorer har lagt deg til som medlem av gruppen.","login":"Logg inn","myfc":"Min Feide Connect","descr":"Beskrivelse","public":"Offentlig","actremoveadmin":"Fjern administrator rettigheter","updated":"Oppdatert","identifier":"Identifikator","created":"Opprettet","leavea":"Ja, forlat denne gruppen","clientsnew":"Registrer ny applikasjon","mygroups":"Mine grupper","deletea":"Slett denne gruppen, jeg vet hva jeg gjør","checking":"Sjekker","grouptypes":"Gruppetyper","invitation":"Invitasjon","memberroles":"Rolletilknytning","rejectinvite":"Avslå gruppeinvitasjonen","groupowner":"Gruppe-eier","invite1":"For å invitere andre til denne gruppen, kan du dele denne URLen:","addedconfirm":"Bekreft, og forbli medlem av gruppen","createclientintro":"Du er i ferd med å registrere en ny applikasjon på Feide Connect.","successinvite":"Du har nå akseptert gruppeinvitasjonen og er medlem av gruppen","invitationtojoin":"Invitasjon til å bli med i gruppe","searchfor":"Søk etter person...","deletegroup":"Slett gruppe","apiref":"API Referanse","logout":"Logg ut","createapigkintro":"Du er i ferd med å registrere et nytt tredjeparts API for å bli tilgjengelig på Feide Connect plattformen.","apigksnew":"Registrer ny API Gatekeeper","contact":"kontakt","reportissues":"rapporter feil","leavegroup":"Forlat gruppe","actremovefromgroup":"Fjern brukeren fra gruppen","createnewgroups":"Opprett nye grupper","savechanges":"Lagre endringer","basicinfo":"Basisinfo","devdash":"Connect Dashboard","clients":"Tjenester","groupidentifier":"Gruppeidentifikator"}